{"allowSleep":true,"autoClearForces":true,"body":[{"angle":0,"angularDamping":"40A00000","angularVelocity":0,"awake":true,"customProperties":[{"bool":false,"name":"freezable"},{"bool":true,"name":"gravityGunAware"}],"fixture":[{"circle":{"center":{"x":"353963A2","y":"360B0ABA"},"radius":"3F5AF75E"},"density":"3F4CCCCD","filter-categoryBits":32,"friction":"3E4CCCCD","name":"fixture"}],"linearDamping":"40A00000","linearVelocity":0,"massData-I":"3F2C2FB9","massData-center":{"x":"353963A2","y":"360B0ABA"},"massData-mass":"3FEB5B02","name":"root","position":0,"type":2},{"angle":"BCFF0380","angularDamping":"40A00000","angularVelocity":0,"awake":true,"customProperties":[{"bool":false,"name":"freezable"},{"bool":true,"name":"gravityGunAware"}],"fixture":[{"circle":{"center":{"x":"35400000","y":"360B0AB8"},"radius":"3F400000"},"density":"3F4CCCCD","filter-categoryBits":32,"friction":"3E4CCCCD","name":"fixture"}],"linearDamping":"40A00000","linearVelocity":0,"massData-I":"3ECB9342","massData-center":{"x":"35400000","y":"360B0AB8"},"massData-mass":"3FB4F4AC","name":"part1","position":{"x":"BF863AD1","y":"3D05B390"},"type":2},{"angle":"3C9A4180","angularDamping":"40A00000","angularVelocity":0,"awake":true,"customProperties":[{"bool":false,"name":"freezable"},{"bool":true,"name":"gravityGunAware"}],"fixture":[{"circle":{"center":{"x":"35400000","y":"360B0AB8"},"radius":"3F400000"},"density":"3F4CCCCD","filter-categoryBits":32,"friction":"3E4CCCCD","name":"fixture"}],"linearDamping":"40A00000","linearVelocity":0,"massData-I":"3ECB9342","massData-center":{"x":"35400000","y":"360B0AB8"},"massData-mass":"3FB4F4AC","name":"part2","position":{"x":"C0064086","y":"3C532230"},"type":2},{"angle":"BC07B400","angularDamping":"40A00000","angularVelocity":0,"awake":true,"customProperties":[{"bool":false,"name":"freezable"},{"bool":true,"name":"gravityGunAware"}],"fixture":[{"circle":{"center":{"x":"35400000","y":"360B0AB8"},"radius":"3F400000"},"density":"3F4CCCCD","filter-categoryBits":32,"friction":"3E4CCCCD","name":"fixture"}],"linearDamping":"40A00000","linearVelocity":0,"massData-I":"3ECB9342","massData-center":{"x":"35400000","y":"360B0AB8"},"massData-mass":"3FB4F4AC","name":"part3","position":{"x":"C049661A","y":"3CB0C140"},"type":2},{"angle":"3D2717C0","angularDamping":"40A00000","angularVelocity":0,"awake":true,"customProperties":[{"bool":false,"name":"freezable"},{"bool":true,"name":"gravityGunAware"}],"fixture":[{"circle":{"center":{"x":"35000000","y":"360B0AB8"},"radius":"3F400000"},"density":"3F4CCCCD","filter-categoryBits":32,"friction":"3E4CCCCD","name":"fixture"}],"linearDamping":"40A00000","linearVelocity":0,"massData-I":"3ECB9342","massData-center":{"x":"35000000","y":"360B0AB8"},"massData-mass":"3FB4F4AC","name":"part4","position":{"x":"C0863EF9","y":"BCADC7C0"},"type":2},{"angle":"3BB40200","angularDamping":"40A00000","angularVelocity":0,"awake":true,"customProperties":[{"bool":false,"name":"freezable"},{"bool":true,"name":"gravityGunAware"}],"fixture":[{"circle":{"center":{"x":"35000000","y":"360B0AB8"},"radius":"3F400000"},"density":"3F4CCCCD","filter-categoryBits":32,"friction":"3E4CCCCD","name":"fixture"}],"linearDamping":"40A00000","linearVelocity":0,"massData-I":"3ECB9342","massData-center":{"x":"35000000","y":"360B0AB8"},"massData-mass":"3FB4F4AC","name":"part5","position":{"x":"C0A7D1EE","y":"BCDCFE00"},"type":2},{"angle":"3D042A00","angularDamping":"40A00000","angularVelocity":0,"awake":true,"customProperties":[{"bool":false,"name":"freezable"},{"bool":true,"name":"gravityGunAware"}],"fixture":[{"circle":{"center":{"x":"35000000","y":"360B0AB8"},"radius":"3F400000"},"density":"3F4CCCCD","filter-categoryBits":32,"friction":"3E4CCCCD","name":"fixture"}],"linearDamping":"40A00000","linearVelocity":0,"massData-I":"3ECB9342","massData-center":{"x":"35000000","y":"360B0AB8"},"massData-mass":"3FB4F4AC","name":"part6","position":{"x":"C0C9608C","y":"BD792400"},"type":2},{"angle":"BBA6A600","angularDamping":"40A00000","angularVelocity":0,"awake":true,"customProperties":[{"bool":false,"name":"freezable"},{"bool":true,"name":"gravityGunAware"}],"fixture":[{"circle":{"center":{"x":"35000000","y":"360B0AB8"},"radius":"3F5AF75E"},"density":"3F4CCCCD","filter-categoryBits":32,"friction":"3E4CCCCD","name":"fixture"}],"linearDamping":"40A00000","linearVelocity":0,"massData-I":"3F2C2FB9","massData-center":{"x":"35000000","y":"360B0AB8"},"massData-mass":"3FEB5B02","name":"tail","position":{"x":"C0EAF381","y":"BD634A40"},"type":2}],"collisionbitplanes":{"names":["general","player","bitplane3","bitplane4","enemy","enemyBuilding","gizmo","bitplane8","bitplane9","bitplane10","bitplane11","bitplane12","bitplane13","bitplane14","bitplane15","bitplane16","bitplane17","bitplane18","bitplane19","bitplane20","bitplane21","bitplane22","bitplane23","bitplane24","bitplane25","bitplane26","bitplane27","bitplane28","bitplane29","bitplane30","bitplane31","bitplane32"]},"continuousPhysics":true,"gravity":0,"image":[{"angle":"BFC90FDB","aspectScale":1,"body":6,"center":{"x":"3D18F1B4","y":"3D8E26EF"},"corners":{"x":["BF1BB892","BF1BB894","3F2ED6C8","3F2ED6CA"],"y":["3F6FC973","BF4C3FB7","BF4C3FB7","3F6FC973"]},"file":"prison1/centipede_body.png","filter":1,"glDrawElements":[0,1,2,2,3,0],"glTexCoordPointer":[0,0,1,0,1,1,0,1],"glVertexPointer":["BF1BB892","3F6FC973","BF1BB894","BF4C3FB7","3F2ED6C8","BF4C3FB7","3F2ED6CA","3F6FC973"],"name":"body","opacity":1,"renderOrder":"C0E00000","scale":"3FA547AE"},{"angle":"BFC90FDB","aspectScale":1,"body":5,"center":{"x":"3D18F1B9","y":"3D8E26F1"},"corners":{"x":["BF1BB891","BF1BB893","3F2ED6C9","3F2ED6CB"],"y":["3F6FC973","BF4C3FB7","BF4C3FB7","3F6FC973"]},"file":"prison1/centipede_body.png","filter":1,"glDrawElements":[0,1,2,2,3,0],"glTexCoordPointer":[0,0,1,0,1,1,0,1],"glVertexPointer":["BF1BB891","3F6FC973","BF1BB893","BF4C3FB7","3F2ED6C9","BF4C3FB7","3F2ED6CB","3F6FC973"],"name":"body","opacity":1,"renderOrder":"C0C00000","scale":"3FA547AE"},{"angle":"BFC90FDB","aspectScale":1,"body":4,"center":{"x":"3D18F1BC","y":"3D8E26F0"},"corners":{"x":["BF1BB891","BF1BB893","3F2ED6C9","3F2ED6CB"],"y":["3F6FC973","BF4C3FB7","BF4C3FB7","3F6FC973"]},"file":"prison1/centipede_body.png","filter":1,"glDrawElements":[0,1,2,2,3,0],"glTexCoordPointer":[0,0,1,0,1,1,0,1],"glVertexPointer":["BF1BB891","3F6FC973","BF1BB893","BF4C3FB7","3F2ED6C9","BF4C3FB7","3F2ED6CB","3F6FC973"],"name":"body","opacity":1,"renderOrder":"C0A00000","scale":"3FA547AE"},{"angle":"BFC90FDB","aspectScale":1,"body":3,"center":{"x":"3D18F1BD","y":"3D8E26EF"},"corners":{"x":["BF1BB891","BF1BB893","3F2ED6C9","3F2ED6CB"],"y":["3F6FC973","BF4C3FB7","BF4C3FB7","3F6FC973"]},"file":"prison1/centipede_body.png","filter":1,"glDrawElements":[0,1,2,2,3,0],"glTexCoordPointer":[0,0,1,0,1,1,0,1],"glVertexPointer":["BF1BB891","3F6FC973","BF1BB893","BF4C3FB7","3F2ED6C9","BF4C3FB7","3F2ED6CB","3F6FC973"],"name":"body","opacity":1,"renderOrder":"C0800000","scale":"3FA547AE"},{"angle":"BFC90FDB","aspectScale":1,"body":2,"center":{"x":"3D18F1BA","y":"3D8E26EC"},"corners":{"x":["BF1BB891","BF1BB893","3F2ED6C9","3F2ED6CB"],"y":["3F6FC972","BF4C3FB8","BF4C3FB8","3F6FC972"]},"file":"prison1/centipede_body.png","filter":1,"glDrawElements":[0,1,2,2,3,0],"glTexCoordPointer":[0,0,1,0,1,1,0,1],"glVertexPointer":["BF1BB891","3F6FC972","BF1BB893","BF4C3FB8","3F2ED6C9","BF4C3FB8","3F2ED6CB","3F6FC972"],"name":"body","opacity":1,"renderOrder":"C0400000","scale":"3FA547AE"},{"angle":"BFC90FDB","aspectScale":1,"body":1,"center":{"x":"3D18F1B9","y":"3D8E26EF"},"corners":{"x":["BF1BB891","BF1BB893","3F2ED6C9","3F2ED6CB"],"y":["3F6FC973","BF4C3FB7","BF4C3FB7","3F6FC973"]},"file":"prison1/centipede_body.png","filter":1,"glDrawElements":[0,1,2,2,3,0],"glTexCoordPointer":[0,0,1,0,1,1,0,1],"glVertexPointer":["BF1BB891","3F6FC973","BF1BB893","BF4C3FB7","3F2ED6C9","BF4C3FB7","3F2ED6CB","3F6FC973"],"name":"body","opacity":1,"renderOrder":"C0000000","scale":"3FA547AE"},{"angle":"40490FDB","aspectScale":1,"body":0,"center":0,"corners":{"x":["3F64CC78","BF64CC7A","BF64CC78","3F64CC7A"],"y":["3F64CC7A","3F64CC78","BF64CC7A","BF64CC78"]},"file":"prison1/squid_eye.png","filter":1,"glDrawElements":[0,1,2,2,3,0],"glTexCoordPointer":[0,0,1,0,1,1,0,1],"glVertexPointer":["3F64CC78","3F64CC7A","BF64CC7A","3F64CC78","BF64CC78","BF64CC7A","3F64CC7A","BF64CC78"],"name":"part","opacity":1,"renderOrder":"BF800000","scale":"3FE4CC79"},{"aspectScale":1,"body":7,"center":0,"corners":{"x":["BF64CC79","3F64CC79","3F64CC79","BF64CC79"],"y":["BF64CC79","BF64CC79","3F64CC79","3F64CC79"]},"file":"prison1/squid_eye.png","filter":1,"glDrawElements":[0,1,2,2,3,0],"glTexCoordPointer":[0,0,1,0,1,1,0,1],"glVertexPointer":["BF64CC79","BF64CC79","3F64CC79","BF64CC79","3F64CC79","3F64CC79","BF64CC79","3F64CC79"],"name":"body","opacity":1,"renderOrder":"BF800000","scale":"3FE4CC79"}],"joint":[{"anchorA":{"x":"3EDC5B1C","y":"BCA08AB4"},"anchorB":{"x":"BF1E7DB8","y":"B9B30000"},"bodyA":1,"bodyB":0,"dampingRatio":"3F333333","frequency":"40000000","name":"br_joint","refAngle":"3CFF0380","type":"weld"},{"anchorA":{"x":"3EDC5B1C","y":"BCA08AB4"},"anchorB":{"x":"BF1E7DB8","y":"B9B30000"},"bodyA":1,"bodyB":0,"enableLimit":true,"enableMotor":false,"jointSpeed":0,"lowerLimit":"BF32B8C2","maxMotorTorque":0,"motorSpeed":0,"name":"br_joint","refAngle":"3CFF0380","type":"revolute","upperLimit":"3F32B8C2"},{"anchorA":0,"anchorB":0,"bodyA":1,"bodyB":0,"maxLength":"3F86683C","name":"br_joint","type":"rope"},{"anchorA":{"x":"3F07D90F","y":"BC134595"},"anchorB":{"x":"BF0477C8","y":"BD0ED73E"},"bodyA":2,"bodyB":1,"dampingRatio":"3F333333","frequency":"40000000","name":"br_joint","refAngle":"BD4CA280","type":"weld"},{"anchorA":{"x":"3F07D90F","y":"BC134595"},"anchorB":{"x":"BF0477C8","y":"BD0ED73E"},"bodyA":2,"bodyB":1,"enableLimit":true,"enableMotor":false,"jointSpeed":0,"lowerLimit":"BEDF66F3","maxMotorTorque":0,"motorSpeed":0,"name":"br_joint","refAngle":"BD4CA280","type":"revolute","upperLimit":"3EDF66F3"},{"anchorA":0,"anchorB":0,"bodyA":2,"bodyB":1,"maxLength":"3F86683C","name":"br_joint","type":"rope"},{"anchorA":{"x":"3F0682BF","y":"BC69FDC9"},"anchorB":{"x":"BF0622AF","y":"B8A26E80"},"bodyA":3,"bodyB":2,"dampingRatio":"3F333333","frequency":"40000000","name":"br_joint","refAngle":"3CDE1B80","type":"weld"},{"anchorA":{"x":"3F0682BF","y":"BC69FDC9"},"anchorB":{"x":"BF0622AF","y":"B8A26E80"},"bodyA":3,"bodyB":2,"enableLimit":true,"enableMotor":false,"jointSpeed":0,"lowerLimit":"BEDF66F3","maxMotorTorque":0,"motorSpeed":0,"name":"br_joint","refAngle":"3CDE1B80","type":"revolute","upperLimit":"3EDF66F3"},{"anchorA":0,"anchorB":0,"bodyA":3,"bodyB":2,"maxLength":"3F86683C","name":"br_joint","type":"rope"},{"anchorA":{"x":"3F0F1E45","y":"BCF3359B"},"anchorB":{"x":"BEF9E85E","y":"BD5BF30C"},"bodyA":4,"bodyB":3,"dampingRatio":"3F333333","frequency":"40000000","name":"br_joint","refAngle":"BD4904C0","type":"weld"},{"anchorA":{"x":"3F0F1E45","y":"BCF3359B"},"anchorB":{"x":"BEF9E85E","y":"BD5BF30C"},"bodyA":4,"bodyB":3,"enableLimit":true,"enableMotor":false,"jointSpeed":0,"lowerLimit":"BEDF66F3","maxMotorTorque":0,"motorSpeed":0,"name":"br_joint","refAngle":"BD4904C0","type":"revolute","upperLimit":"3EDF66F3"},{"anchorA":0,"anchorB":0,"bodyA":4,"bodyB":3,"maxLength":"3F86683C","name":"br_joint","type":"rope"},{"anchorA":{"x":"3F0B990B","y":"BCACBD14"},"anchorB":{"x":"BF011BD9","y":"BB577F70"},"bodyA":5,"bodyB":4,"dampingRatio":"3F333333","frequency":"40000000","name":"br_joint","refAngle":"3D109780","type":"weld"},{"anchorA":{"x":"3F0B990B","y":"BCACBD14"},"anchorB":{"x":"BF011BD9","y":"BB577F70"},"bodyA":5,"bodyB":4,"enableLimit":true,"enableMotor":false,"jointSpeed":0,"lowerLimit":"BEDF66F3","maxMotorTorque":0,"motorSpeed":0,"name":"br_joint","refAngle":"3D109780","type":"revolute","upperLimit":"3EDF66F3"},{"anchorA":0,"anchorB":0,"bodyA":5,"bodyB":4,"maxLength":"3F86683C","name":"br_joint","type":"rope"},{"anchorA":{"x":"3F0EC90F","y":"BD0AF0EC"},"anchorB":{"x":"BEFB113C","y":"BD40C7B8"},"bodyA":6,"bodyB":5,"dampingRatio":"3F333333","frequency":"40000000","name":"br_joint","refAngle":"BCDB5380","type":"weld"},{"anchorA":{"x":"3F0EC90F","y":"BD0AF0EC"},"anchorB":{"x":"BEFB113C","y":"BD40C7B8"},"bodyA":6,"bodyB":5,"enableLimit":true,"enableMotor":false,"jointSpeed":0,"lowerLimit":"BEDF66F3","maxMotorTorque":0,"motorSpeed":0,"name":"br_joint","refAngle":"BCDB5380","type":"revolute","upperLimit":"3EDF66F3"},{"anchorA":0,"anchorB":0,"bodyA":6,"bodyB":5,"maxLength":"3F86683C","name":"br_joint","type":"rope"},{"anchorA":{"x":"3F2350EA","y":"BD17A62C"},"anchorB":{"x":"BED31EE5","y":"BCB149CE"},"bodyA":7,"bodyB":6,"dampingRatio":"3F333333","frequency":"40000000","name":"br_joint","refAngle":"3D18FEC0","type":"weld"},{"anchorA":{"x":"3F2350EA","y":"BD17A62C"},"anchorB":{"x":"BED31EE5","y":"BCB149CE"},"bodyA":7,"bodyB":6,"enableLimit":true,"enableMotor":false,"jointSpeed":0,"lowerLimit":"BEDF66F3","maxMotorTorque":0,"motorSpeed":0,"name":"br_joint","refAngle":"3D18FEC0","type":"revolute","upperLimit":"3EDF66F3"},{"anchorA":0,"anchorB":0,"bodyA":7,"bodyB":6,"maxLength":"3F86683C","name":"br_joint","type":"rope"}],"positionIterations":3,"stepsPerSecond":60.0,"subStepping":false,"velocityIterations":8,"warmStarting":true}
