{"allowSleep":true,"autoClearForces":true,"body":[{"angle":0,"angularVelocity":0,"awake":true,"customProperties":[{"name":"class","string":"rock"},{"bool":true,"name":"glassy"}],"fixture":[{"circle":{"center":{"x":"36000006","y":"B480000F"},"radius":"3FF33333"},"customProperties":[{"name":"class","string":"polygon"}],"density":"40A00000","filter-categoryBits":128,"filter-maskBits":65407,"friction":"3E4CCCCD","name":"points"}],"linearVelocity":0,"massData-I":"42CCB52F","massData-center":{"x":"36000006","y":"B480000F"},"massData-mass":"4262D2B0","name":"door1_wheel","position":{"x":"C10BAB3A","y":0},"type":2},{"angle":0,"angularVelocity":0,"awake":true,"customProperties":[{"name":"class","string":"rock"},{"bool":true,"name":"glassy"}],"fixture":[{"customProperties":[{"name":"class","string":"polygon"}],"density":"40A00000","filter-categoryBits":128,"filter-maskBits":65407,"friction":"3E4CCCCD","name":"points","polygon":{"vertices":{"x":["413E4AFF","413E4AFF","C13E4AEB","C13E4A82"],"y":["BFA19FA5","3FA1A737","3FA1A78B","BFA19FA5"]}}}],"linearVelocity":0,"massData-I":"465FC9CC","massData-center":{"x":"37E24200","y":"38F95D45"},"massData-mass":"43963046","name":"door1_bar","position":0,"type":2},{"angle":0,"angularVelocity":0,"awake":true,"customProperties":[{"name":"class","string":"rock"}],"linearVelocity":0,"name":"door1_dummy","position":{"x":"40000000","y":"C0000000"},"type":0}],"collisionbitplanes":{"names":["general","player","ally","rock","enemy","enemyBuilding","gizmo","custom1","custom2","garbage","vehicle","enemyRock","bitplane13","bitplane14","bitplane15","bitplane16","bitplane17","bitplane18","bitplane19","bitplane20","bitplane21","bitplane22","bitplane23","bitplane24","bitplane25","bitplane26","bitplane27","bitplane28","bitplane29","bitplane30","bitplane31","bitplane32"]},"continuousPhysics":true,"gravity":0,"image":[{"aspectScale":"40151EB8","body":1,"center":{"x":"BD381E00","y":"3C907659"},"corners":{"x":["C13ED8E2","413D68A6","413D68A6","C13ED8E2"],"y":["BFA0F15A","BFA0F15A","3FA5750C","3FA5750C"]},"file":"factory1/bar1.png","filter":1,"glDrawElements":[0,1,2,2,3,0],"glTexCoordPointer":[0,0,1,0,1,1,0,1],"glVertexPointer":["C13ED8E2","BFA0F15A","413D68A6","BFA0F15A","413D68A6","3FA5750C","C13ED8E2","3FA5750C"],"name":"image","opacity":"3F000000","renderOrder":"42B60000","scale":"40233333"},{"aspectScale":1,"body":0,"center":0,"corners":{"x":["C0000000","40000000","40000000","C0000000"],"y":["C0000000","C0000000","40000000","40000000"]},"file":"factory1/cogwheel1.png","filter":1,"glDrawElements":[0,1,2,2,3,0],"glTexCoordPointer":[0,0,1,0,1,1,0,1],"glVertexPointer":["C0000000","C0000000","40000000","C0000000","40000000","40000000","C0000000","40000000"],"name":"image","opacity":"3F000000","renderOrder":"42B80000","scale":"40800000"}],"joint":[{"anchorA":{"x":"C0000000","y":"40000000"},"anchorB":0,"bodyA":2,"bodyB":1,"enableLimit":true,"enableMotor":true,"localAxisA":{"x":"BF800000","y":0},"lowerLimit":0,"maxMotorForce":"49742400","motorSpeed":"C1F00000","name":"door1_bar_joint","refAngle":0,"type":"prismatic","upperLimit":"419CC77A"},{"anchorA":{"x":"C12BAB3A","y":"40000000"},"anchorB":0,"bodyA":2,"bodyB":0,"enableLimit":false,"enableMotor":false,"jointSpeed":0,"lowerLimit":0,"maxMotorTorque":0,"motorSpeed":0,"name":"door1_wheel_joint","refAngle":0,"type":"revolute","upperLimit":0}],"positionIterations":3,"stepsPerSecond":60.0,"subStepping":false,"velocityIterations":8,"warmStarting":true}
