{"allowSleep":true,"autoClearForces":true,"body":[{"angle":0,"angularDamping":"40000000","angularVelocity":0,"awake":true,"customProperties":[{"name":"class","string":"rock"},{"bool":true,"name":"gravityGunAware"}],"fixture":[{"customProperties":[{"name":"class","string":"polygon"}],"density":1,"filter-categoryBits":264,"filter-maskBits":65279,"friction":"3E4CCCCD","name":"fixture","polygon":{"vertices":{"x":["3FAA4E38","3F38B3D2","BF26A4BF","BFAAA435","BFAF771C","BF583A70","3F61CC6A","3FA98FFB"],"y":["3F9B7273","3FCA4BCA","3FCB2910","3F8438A2","BF9A594A","BFC44FE6","BFC16A53","BFA00CFA"]}},"restitution":"3E4CCCCD"}],"linearDamping":"40000000","linearVelocity":0,"massData-I":"4122F3B1","massData-center":{"x":"B34C0001","y":"B4120001"},"massData-mass":"40FC0798","name":"robopart2","position":0,"type":2}],"collisionbitplanes":{"names":["general","player","ally","rock","enemy","enemyBuilding","gizmo","custom1","custom2","bitplane10","bitplane11","bitplane12","bitplane13","bitplane14","bitplane15","bitplane16","bitplane17","bitplane18","bitplane19","bitplane20","bitplane21","bitplane22","bitplane23","bitplane24","bitplane25","bitplane26","bitplane27","bitplane28","bitplane29","bitplane30","bitplane31","bitplane32"]},"continuousPhysics":true,"gravity":0,"image":[{"aspectScale":1,"body":0,"center":{"x":"BD8A0081","y":"3C87D0E5"},"corners":{"x":["BFBA50AC","3FA9109C","3FA9109C","BFBA50AC"],"y":["BFC8F3C0","BFC8F3C0","3FCD3248","3FCD3248"]},"file":"factory4/robopart3.png","filter":1,"glDrawElements":[0,1,2,2,3,0],"glTexCoordPointer":[0,0,1,0,1,1,0,1],"glVertexPointer":["BFBA50AC","BFC8F3C0","3FA9109C","BFC8F3C0","3FA9109C","3FCD3248","BFBA50AC","3FCD3248"],"name":"image","opacity":"3F000000","renderOrder":"40C00000","scale":"404B1304"}],"positionIterations":3,"stepsPerSecond":60.0,"subStepping":false,"velocityIterations":8,"warmStarting":true}
