{"allowSleep":true,"autoClearForces":true,"body":[{"angle":0,"angularVelocity":0,"awake":true,"bullet":true,"customProperties":[{"bool":true,"name":"freezable"},{"float":"40A00000","name":"freezeRadius"}],"fixedRotation":true,"fixture":[{"circle":{"center":0,"radius":"3E99999A"},"density":"3E4CCCCD","filter-groupIndex":-100,"name":"root"}],"linearVelocity":0,"massData-mass":"3D679F95","name":"root","position":0,"type":2}],"collisionbitplanes":{"names":["bitplane1","bitplane2","bitplane3","bitplane4","bitplane5","bitplane6","bitplane7","bitplane8","bitplane9","bitplane10","bitplane11","bitplane12","bitplane13","bitplane14","bitplane15","bitplane16","bitplane17","bitplane18","bitplane19","bitplane20","bitplane21","bitplane22","bitplane23","bitplane24","bitplane25","bitplane26","bitplane27","bitplane28","bitplane29","bitplane30","bitplane31","bitplane32"]},"continuousPhysics":true,"gravity":0,"image":[{"angle":"BFC90FDB","aspectScale":1,"body":0,"center":0,"corners":{"x":["BEA5A379","BEA5A379","3EA5A379","3EA5A379"],"y":["3EA5A379","BEA5A379","BEA5A379","3EA5A379"]},"file":"common2/particle_basic.png","filter":1,"glDrawElements":[0,1,2,2,3,0],"glTexCoordPointer":[0,0,1,0,1,1,0,1],"glVertexPointer":["BEA5A379","3EA5A379","BEA5A379","BEA5A379","3EA5A379","BEA5A379","3EA5A379","3EA5A379"],"name":"image1","opacity":1,"renderOrder":"40E00000","scale":"3F25A379"},{"angle":"BFC90FDB","aspectScale":1,"body":0,"center":{"x":"BE845939","y":"2700000F"},"corners":{"x":["BF0283A0","BF0283A0","BBEACC40","BBEACC40"],"y":["3E80AE08","BE80AE08","BE80AE08","3E80AE08"]},"file":"common2/particle_basic.png","filter":1,"glDrawElements":[0,1,2,2,3,0],"glTexCoordPointer":[0,0,1,0,1,1,0,1],"glVertexPointer":["BF0283A0","3E80AE08","BF0283A0","BE80AE08","BBEACC40","BE80AE08","BBEACC40","3E80AE08"],"name":"image2","opacity":1,"renderOrder":"40E00000","scale":"3F00AE08"},{"angle":"BFC90FDB","aspectScale":1,"body":0,"center":{"x":"BEE3E490","y":"26030938"},"corners":{"x":["BF239F62","BF239F62","BE808A5C","BE808A5B"],"y":["3E46B46A","BE46B468","BE46B46A","3E46B468"]},"file":"common2/particle_basic.png","filter":1,"glDrawElements":[0,1,2,2,3,0],"glTexCoordPointer":[0,0,1,0,1,1,0,1],"glVertexPointer":["BF239F62","3E46B46A","BF239F62","BE46B468","BE808A5C","BE46B46A","BE808A5B","3E46B468"],"name":"image3","opacity":1,"renderOrder":"40E00000","scale":"3EC6B469"},{"aspectScale":1,"body":0,"center":0,"corners":{"x":["BE65087D","3E65087D","3E65087D","BE65087D"],"y":["BE728176","BE728176","3E728176","3E728176"]},"customProperties":[{"int":10,"name":"numRays"},{"name":"light","string":"point"},{"bool":false,"name":"diffuse"},{"bool":false,"name":"dynamic"},{"bool":true,"name":"visible"},{"bool":true,"name":"xray"},{"float":"40E00000","name":"coneAngle"},{"float":"3F000000","name":"distance"},{"float":"40000000","name":"intensity"},{"float":"40000000","name":"softLength"}],"file":"l.png","filter":1,"glDrawElements":[0,1,2,2,3,0],"glTexCoordPointer":[0,0,1,0,1,1,0,1],"glVertexPointer":["BE65087D","BE728176","3E65087D","BE728176","3E65087D","3E728176","BE65087D","3E728176"],"name":"light1","opacity":1,"renderOrder":"42C80000","scale":"3EF28176"},{"aspectScale":1,"body":0,"center":{"x":"BEE3E490","y":0},"corners":{"x":["BF060ED7","BEBBAB72","BEBBAB72","BF060ED7"],"y":["BDAA5B54","BDAA5B54","3DAA5B54","3DAA5B54"]},"customProperties":[{"int":10,"name":"numRays"},{"name":"light","string":"point"},{"bool":false,"name":"diffuse"},{"bool":false,"name":"dynamic"},{"bool":true,"name":"visible"},{"bool":true,"name":"xray"},{"float":"40E00000","name":"coneAngle"},{"float":"3E99999A","name":"distance"},{"float":"40000000","name":"intensity"},{"float":"40000000","name":"softLength"}],"file":"l.png","filter":1,"glDrawElements":[0,1,2,2,3,0],"glTexCoordPointer":[0,0,1,0,1,1,0,1],"glVertexPointer":["BF060ED7","BDAA5B54","BEBBAB72","BDAA5B54","BEBBAB72","3DAA5B54","BF060ED7","3DAA5B54"],"name":"light3","opacity":1,"renderOrder":"42C80000","scale":"3E2A5B54"},{"aspectScale":1,"body":0,"center":{"x":"BE84592E","y":0},"corners":{"x":["BEAF4072","BE32E3D4","BE32E3D4","BEAF4072"],"y":["BDB5B55E","BDB5B55E","3DB5B55E","3DB5B55E"]},"customProperties":[{"int":10,"name":"numRays"},{"name":"light","string":"point"},{"bool":false,"name":"diffuse"},{"bool":false,"name":"dynamic"},{"bool":true,"name":"visible"},{"bool":true,"name":"xray"},{"float":"40E00000","name":"coneAngle"},{"float":"3ECCCCCD","name":"distance"},{"float":"40000000","name":"intensity"},{"float":"40000000","name":"softLength"}],"file":"l.png","filter":1,"glDrawElements":[0,1,2,2,3,0],"glTexCoordPointer":[0,0,1,0,1,1,0,1],"glVertexPointer":["BEAF4072","BDB5B55E","BE32E3D4","BDB5B55E","BE32E3D4","3DB5B55E","BEAF4072","3DB5B55E"],"name":"light2","opacity":1,"renderOrder":"42C80000","scale":"3E35B55E"}],"positionIterations":3,"stepsPerSecond":60.0,"subStepping":false,"velocityIterations":8,"warmStarting":true}
